govuk_design_system_mcp/__init__.py
govuk_design_system_mcp/data_fetcher.py
govuk_design_system_mcp/server.py
govuk_design_system_mcp-0.1.1.dist-info/METADATA
govuk_design_system_mcp-0.1.1.dist-info/WHEEL
govuk_design_system_mcp-0.1.1.dist-info/entry_points.txt
govuk_design_system_mcp-0.1.1.dist-info/licenses/LICENSE
govuk_design_system_mcp-0.1.1.dist-info/RECORD
