Metadata-Version: 2.4
Name: govuk-design-system-mcp
Version: 0.1.1
Summary: MCP server exposing GOV.UK Design System documentation to AI agents
License-Expression: MIT
License-File: LICENSE
Requires-Python: >=3.10
Requires-Dist: httpx<1.0.0,>=0.27.0
Requires-Dist: mcp<2.0.0,>=1.0.0
